celery_pydantic/__init__.py
celery_pydantic/serializer.py
celery_pydantic-0.1.0.dist-info/licenses/LICENSE
celery_pydantic-0.1.0.dist-info/METADATA
celery_pydantic-0.1.0.dist-info/WHEEL
celery_pydantic-0.1.0.dist-info/top_level.txt
celery_pydantic-0.1.0.dist-info/RECORD
