Metadata-Version: 2.4
Name: celery-pydantic
Version: 0.1.0
Summary: A library for serializing Pydantic models in Celery tasks
Home-page: https://github.com/yourusername/celery_pydantic
Author: Noel Wilson
License: MIT
Requires-Python: >=3.9
License-File: LICENSE
Requires-Dist: celery>=5.0.0
Requires-Dist: pydantic>=2.0.0
Requires-Dist: kombu>=5.0.0
Provides-Extra: dev
Requires-Dist: pytest>=7.0.0; extra == "dev"
Requires-Dist: pytest-cov>=4.0.0; extra == "dev"
Requires-Dist: black>=23.0.0; extra == "dev"
Requires-Dist: isort>=5.0.0; extra == "dev"
Requires-Dist: mypy>=1.0.0; extra == "dev"
Requires-Dist: ruff>=0.1.0; extra == "dev"
Dynamic: home-page
Dynamic: license-file
Dynamic: requires-python
